HISTORY.rst
LICENSE
MANIFEST.in
README.rst
setup.cfg
setup.py
bin/binclock.py
binary_clock/__init__.py
binary_clock/binclockWrapper.py
binary_clock.egg-info/PKG-INFO
binary_clock.egg-info/SOURCES.txt
binary_clock.egg-info/dependency_links.txt
binary_clock.egg-info/not-zip-safe
binary_clock.egg-info/top_level.txt
images/animation_flat.gif
images/animation_image.gif