Metadata-Version: 1.1
Name: binary-clock
Version: 0.0.2
Summary: Truly Binary Clock
Home-page: https://github.com/zeycus/binary_clock/
Author: Miguel Garcia (aka Zeycus)
Author-email: zeycus@gmail.com
License: MIT
Keywords: binary clock
Platform: Windows
Platform: Linux
Classifier: Development Status :: 4 - Beta
Classifier: License :: OSI Approved :: MIT License
Classifier: Programming Language :: Python :: 3.5
Classifier: Topic :: Utilities
